ACID_code_v2/__init__.py
ACID_code_v2/acid.py
ACID_code_v2/lsd.py
ACID_code_v2/mcmc.py
ACID_code_v2/profiles.py
ACID_code_v2/result.py
ACID_code_v2/utils.py
acid_code_v2-1.3.0.dist-info/licenses/LICENSE
acid_code_v2-1.3.0.dist-info/METADATA
acid_code_v2-1.3.0.dist-info/WHEEL
acid_code_v2-1.3.0.dist-info/top_level.txt
acid_code_v2-1.3.0.dist-info/RECORD
