Metadata-Version: 2.4
Name: ACID_code_v2
Version: 1.3.0
Summary: Returns line profiles from input spectra by fitting the stellar continuum and performing LSD
Author: Lucy Dolan
Author-email: Benjamin Cadell <bcadell01@qub.ac.uk>
License-Expression: MIT
Project-URL: Homepage, https://github.com/Benjamin-Cadell/ACID
Keywords: lsd,least squares deconvolution,fitting,ACID
Classifier: Programming Language :: Python :: 3
Classifier: Operating System :: POSIX
Requires-Python: >=3.8
License-File: LICENSE
Requires-Dist: numpy
Requires-Dist: emcee
Requires-Dist: matplotlib
Requires-Dist: scipy
Requires-Dist: astropy
Requires-Dist: tqdm
Requires-Dist: psutil
Requires-Dist: corner
Requires-Dist: beartype
Provides-Extra: docs
Requires-Dist: sphinx_rtd_theme; extra == "docs"
Dynamic: license-file
